{
    "Symbol": "AAMI",
    "AssetType": "Common Stock",
    "Name": "Acadian Asset Management Inc",
    "Description": "BrightSphere Investment Group Inc. is a publically owned asset management holding company. The company is headquartered in Boston, Massachusetts.",
    "CIK": "1748824",
    "Exchange": "NYSE",
    "Currency": "USD",
    "Country": "USA",
    "Sector": "FINANCE",
    "Industry": "INVESTMENT ADVICE",
    "Address": "200 CLAREDON ST, 53RD FLOOR, BOSTON, MA, US",
    "OfficialSite": "https://www.bsig.com",
    "FiscalYearEnd": "December",
    "LatestQuarter": "2024-09-30",
    "MarketCapitalization": "964295000",
    "EBITDA": "134400000",
    "PERatio": "15.76",
    "PEGRatio": "None",
    "BookValue": "-0.48",
    "DividendPerShare": "0.04",
    "DividendYield": "0.0015",
    "EPS": "1.64",
    "RevenuePerShareTTM": "12.09",
    "ProfitMargin": "0.139",
    "OperatingMarginTTM": "0.219",
    "ReturnOnAssetsTTM": "0.131",
    "ReturnOnEquityTTM": "0.511",
    "RevenueTTM": "469000000",
    "GrossProfitTTM": "0",
    "DilutedEPSTTM": "1.64",
    "QuarterlyEarningsGrowthYOY": "-0.022",
    "QuarterlyRevenueGrowthYOY": "0.147",
    "AnalystTargetPrice": "29",
    "AnalystRatingStrongBuy": "0",
    "AnalystRatingBuy": "0",
    "AnalystRatingHold": "2",
    "AnalystRatingSell": "1",
    "AnalystRatingStrongSell": "0",
    "TrailingPE": "15.76",
    "ForwardPE": "8.64",
    "PriceToSalesRatioTTM": "2.056",
    "PriceToBookRatio": "40.73",
    "EVToRevenue": "2.671",
    "EVToEBITDA": "8.92",
    "Beta": "1.421",
    "52WeekHigh": "31.51",
    "52WeekLow": "21.42",
    "50DayMovingAverage": "28.85",
    "200DayMovingAverage": "24.81",
    "SharesOutstanding": "37317900",
    "DividendDate": "None",
    "ExDividendDate": "2024-12-13"
}