{
    "Symbol": "KO",
    "AssetType": "Common Stock",
    "Name": "The Coca-Cola Company",
    "Description": "The Coca-Cola Company is an American multinational beverage corporation incorporated under Delaware's General Corporation Law and headquartered in Atlanta, Georgia. The Coca-Cola Company has interests in the manufacturing, retailing, and marketing of nonalcoholic beverage concentrates and syrups.",
    "CIK": "21344",
    "Exchange": "NYSE",
    "Currency": "USD",
    "Country": "USA",
    "Sector": "MANUFACTURING",
    "Industry": "BEVERAGES",
    "Address": "ONE COCA COLA PLAZA, ATLANTA, GA, US",
    "OfficialSite": "https://www.coca-colacompany.com",
    "FiscalYearEnd": "December",
    "LatestQuarter": "2024-09-30",
    "MarketCapitalization": "275139199000",
    "EBITDA": "14831000000",
    "PERatio": "26.5",
    "PEGRatio": "2.619",
    "BookValue": "6.15",
    "DividendPerShare": "1.915",
    "DividendYield": "0.0313",
    "EPS": "2.41",
    "RevenuePerShareTTM": "10.75",
    "ProfitMargin": "0.225",
    "OperatingMarginTTM": "0.302",
    "ReturnOnAssetsTTM": "0.0844",
    "ReturnOnEquityTTM": "0.372",
    "RevenueTTM": "46365999000",
    "GrossProfitTTM": "28021000000",
    "DilutedEPSTTM": "2.41",
    "QuarterlyEarningsGrowthYOY": "-0.07",
    "QuarterlyRevenueGrowthYOY": "-0.008",
    "AnalystTargetPrice": "71.63",
    "AnalystRatingStrongBuy": "6",
    "AnalystRatingBuy": "12",
    "AnalystRatingHold": "6",
    "AnalystRatingSell": "0",
    "AnalystRatingStrongSell": "0",
    "TrailingPE": "26.5",
    "ForwardPE": "20.96",
    "PriceToSalesRatioTTM": "5.93",
    "PriceToBookRatio": "10.06",
    "EVToRevenue": "6.36",
    "EVToEBITDA": "19.06",
    "Beta": "0.62",
    "52WeekHigh": "72.48",
    "52WeekLow": "56.66",
    "50DayMovingAverage": "62.62",
    "200DayMovingAverage": "65.14",
    "SharesOutstanding": "4307800000",
    "DividendDate": "2024-12-16",
    "ExDividendDate": "2024-11-29"
}